lgbsttracker/__init__.py
lgbsttracker/cli.py
lgbsttracker/db.py
lgbsttracker/entities/__init__.py
lgbsttracker/entities/experiment.py
lgbsttracker/errors.py
lgbsttracker/exceptions.py
lgbsttracker/services/__init__.py
lgbsttracker/services/store/__init__.py
lgbsttracker/services/store/_experiment_registry/__init__.py
lgbsttracker/services/store/_experiment_registry/registry.py
lgbsttracker/services/store/_experiment_registry/service.py
lgbsttracker/services/store/_experiment_registry/utils.py
lgbsttracker/services/store/registry.py
lgbsttracker/store/__init__.py
lgbsttracker/store/db/__init__.py
lgbsttracker/store/db/db_types.py
lgbsttracker/store/db/sql_background.py
lgbsttracker/store/db/sql_base.py
lgbsttracker/store/db/sql_crud_base.py
lgbsttracker/store/db/sql_database.py
lgbsttracker/store/db/utils.py
lgbsttracker/store/db_migrations/README
lgbsttracker/store/db_migrations/alembic.ini
lgbsttracker/store/db_migrations/env.py
lgbsttracker/store/db_migrations/script.py.mako
lgbsttracker/store/db_migrations/versions/ae2444ccb82a_initial_db.py
lgbsttracker/store/experiment/__init__.py
lgbsttracker/store/experiment/abstract_store.py
lgbsttracker/store/experiment/dbmodels/__init__.py
lgbsttracker/store/experiment/dbmodels/experiment.py
lgbsttracker/store/experiment/sqlachemy_store.py
lgbsttracker/utils/__init__.py
lgbsttracker/utils/env.py
lgbsttracker/utils/logging_utils.py
lgbsttracker/utils/uri.py
lgbsttracker/utils/validation.py
lgbsttracker/version.py
lgbsttracker-0.0.4.dist-info/entry_points.txt
lgbsttracker-0.0.4.dist-info/LICENSE
lgbsttracker-0.0.4.dist-info/WHEEL
lgbsttracker-0.0.4.dist-info/METADATA
lgbsttracker-0.0.4.dist-info/RECORD
